fennec_ml/__init__.py
fennec_ml/data_utils.py
fennec_ml-0.5.0.dist-info/licenses/LICENSE
fennec_ml-0.5.0.dist-info/METADATA
fennec_ml-0.5.0.dist-info/WHEEL
fennec_ml-0.5.0.dist-info/top_level.txt
fennec_ml-0.5.0.dist-info/RECORD
