Metadata-Version: 2.4
Name: fennec-ml
Version: 0.5.0
Summary: Machine Learning tools for LETU FENNEC senior design team
Author-email: nontopus <micahb.yarbrough@gmail.com>
License-Expression: MIT
Project-URL: Homepage, https://github.com/afdavisLETU/fennec-ml
Requires-Python: >=3.8
License-File: LICENSE
Requires-Dist: numpy
Requires-Dist: pandas
Requires-Dist: openpyxl
Requires-Dist: scikit-learn
Dynamic: license-file
